CHANGELOG.txt
LICENSE.txt
README.txt
setup.py
Extensions/Install.py
jsl10n/__init__.py
jsl10n/configure.zcml
jsl10n.egg-info/PKG-INFO
jsl10n.egg-info/SOURCES.txt
jsl10n.egg-info/dependency_links.txt
jsl10n.egg-info/not-zip-safe
jsl10n.egg-info/requires.txt
jsl10n.egg-info/top_level.txt
jsl10n/browser/__init__.py
jsl10n/browser/configure.zcml
jsl10n/browser/jstranslate.py
jsl10n/browser/javascript/jquery.cookie-1.0.js
jsl10n/browser/javascript/jsl10n.js
jsl10n/profiles/default/jsregistry.xml