Metadata-Version: 1.0
Name: jsl10n
Version: 1.1
Summary: Javascript localization using Zope i18n
Home-page: http://svn.plone.org/svn/collective/jsl10n
Author: Isotoma Limited
Author-email: richard.mitchell@isotoma.com
License: Apache 2.0
Keywords: zope plone javascript l10n localization i18n internationalization
Platform: UNKNOWN
Classifier: Development Status :: 4 - Beta
Classifier: Intended Audience :: Developers
Classifier: Programming Language :: Python
Classifier: Framework :: Zope2
Classifier: Framework :: Plone
Classifier: Topic :: Software Development :: Libraries :: Python Modules
